QCMFuncs/.gitignore
QCMFuncs/DMA_functions.py
QCMFuncs/QCM_functions.py
QCMFuncs/__init__.py
QCMFuncs/fatigue_functions.py
QCMFuncs/example_data/polymer_h5/polymer.h5
rheoQCM/MainWindow.py
rheoQCM/UISettings.py
rheoQCM/UI_source_rc.py
rheoQCM/__init__.py
rheoQCM/_version.py
rheoQCM/device.py
rheoQCM/icon.ico
rheoQCM/lazy_imports.py
rheoQCM/logging_config.py
rheoQCM/main.py
rheoQCM/rheoQCM.bat
rheoQCM/rheoQCM.py
rheoQCM/core/__init__.py
rheoQCM/core/analysis.py
rheoQCM/core/bayesian.py
rheoQCM/core/jax_config.py
rheoQCM/core/model.py
rheoQCM/core/multilayer.py
rheoQCM/core/physics.py
rheoQCM/core/signal.py
rheoQCM/core/uncertainty.py
rheoQCM/dll/AccessMyVNAdll.dll
rheoQCM/gui/__init__.py
rheoQCM/gui/dialogs.py
rheoQCM/gui/widgets.py
rheoQCM/gui/workers.py
rheoQCM/io/__init__.py
rheoQCM/io/base.py
rheoQCM/io/excel_handler.py
rheoQCM/io/hdf5_handler.py
rheoQCM/io/json_handler.py
rheoQCM/modules/AccessMyVNA.py
rheoQCM/modules/DataSaver.py
rheoQCM/modules/MatplotlibWidget.py
rheoQCM/modules/PeakTracker.py
rheoQCM/modules/QCM.py
rheoQCM/modules/TempDevices.py
rheoQCM/modules/TempModules.py
rheoQCM/modules/UIModules.py
rheoQCM/modules/__init__.py
rheoQCM/modules/matplotlibplugin.py
rheoQCM/services/__init__.py
rheoQCM/services/base.py
rheoQCM/services/hardware.py
rheoQCM/services/plotting.py
rheoQCM/services/settings.py
rheoQCM/ui/__init__.py
rheoqcm-0.1.0.dist-info/licenses/LICENSE
rheoqcm-0.1.0.dist-info/METADATA
rheoqcm-0.1.0.dist-info/WHEEL
rheoqcm-0.1.0.dist-info/entry_points.txt
rheoqcm-0.1.0.dist-info/top_level.txt
rheoqcm-0.1.0.dist-info/RECORD
