Metadata-Version: 2.4
Name: rheoQCM
Version: 0.1.0
Summary: QCM-D data acquisition and analysis software with rheological modeling
Author-email: Wei Chen <wchen@anl.gov>
Maintainer-email: Wei Chen <wchen@anl.gov>
License: MIT License
Project-URL: Homepage, https://github.com/imewei/RheoQCM
Project-URL: Bug Tracker, https://github.com/imewei/RheoQCM/issues
Project-URL: Source Code, https://github.com/imewei/RheoQCM
Classifier: Development Status :: 4 - Beta
Classifier: Intended Audience :: Science/Research
Classifier: Topic :: Scientific/Engineering :: Physics
Classifier: License :: OSI Approved :: MIT License
Classifier: Programming Language :: Python :: 3
Classifier: Programming Language :: Python :: 3.12
Classifier: Programming Language :: Python :: 3.13
Classifier: Operating System :: OS Independent
Requires-Python: >=3.12
License-File: LICENSE
Requires-Dist: numpy>=2.2.0
Requires-Dist: scipy>=1.14.0
Requires-Dist: pandas>=2.2.0
Requires-Dist: matplotlib>=3.9.0
Requires-Dist: jax>=0.8.0
Requires-Dist: jaxlib>=0.8.0
Requires-Dist: optimistix>=0.0.6
Requires-Dist: nlsq>=0.4.1
Requires-Dist: numpyro>=0.14.0
Requires-Dist: arviz>=0.18.0
Requires-Dist: interpax
Requires-Dist: h5py<4.0.0,>=3.12.0
Requires-Dist: hdf5storage>=0.1.19
Requires-Dist: openpyxl<4.0.0,>=3.1.0
Requires-Dist: xlsxwriter<4.0.0,>=3.2.0
Requires-Dist: xlrd<3.0.0,>=2.0.0
Requires-Dist: packaging>=24.0
Requires-Dist: platformdirs>=3.0.0
Provides-Extra: dev
Requires-Dist: pytest>=8.0.0; extra == "dev"
Requires-Dist: pytest-cov>=5.0.0; extra == "dev"
Requires-Dist: pytest-qt>=4.4.0; extra == "dev"
Requires-Dist: pytest-xdist>=3.5.0; extra == "dev"
Requires-Dist: hypothesis>=6.100.0; extra == "dev"
Requires-Dist: black>=24.0.0; extra == "dev"
Requires-Dist: ruff>=0.5.0; extra == "dev"
Requires-Dist: mypy>=1.10.0; extra == "dev"
Requires-Dist: pre-commit>=3.7.0; extra == "dev"
Requires-Dist: ipython>=8.26.0; extra == "dev"
Requires-Dist: jupyter>=1.0.0; extra == "dev"
Requires-Dist: build>=1.2.0; extra == "dev"
Requires-Dist: twine>=6.0.0; extra == "dev"
Provides-Extra: gui
Requires-Dist: PyQt6>=6.6.0; extra == "gui"
Provides-Extra: hardware
Requires-Dist: nidaqmx>=1.0.0; extra == "hardware"
Requires-Dist: pypiwin32>=223; sys_platform == "win32" and extra == "hardware"
Provides-Extra: fallback
Requires-Dist: mpmath>=1.3.0; extra == "fallback"
Provides-Extra: docs
Requires-Dist: sphinx>=8.0; extra == "docs"
Requires-Dist: myst-parser>=4.0; extra == "docs"
Requires-Dist: sphinxcontrib-bibtex>=2.6; extra == "docs"
Requires-Dist: linkify-it-py>=2.0; extra == "docs"
Provides-Extra: all
Requires-Dist: rheoQCM[dev,docs,fallback,gui,hardware]; extra == "all"
Dynamic: license-file
